example_pkg/__init__.py
example_pkg/you.py
BDPefg-0.0.1.dist-info/LICENSE
BDPefg-0.0.1.dist-info/METADATA
BDPefg-0.0.1.dist-info/WHEEL
BDPefg-0.0.1.dist-info/top_level.txt
BDPefg-0.0.1.dist-info/RECORD
